jict/__init__.py
jict/helpers.py
jict/jict.py
jict/raw_tags.py
jict/soup.py
jict/tag_attrs.py
jict/yaml_to_note.py
jict-3.0.2.dist-info/LICENSE.TXT
jict-3.0.2.dist-info/METADATA
jict-3.0.2.dist-info/WHEEL
jict-3.0.2.dist-info/top_level.txt
jict-3.0.2.dist-info/RECORD
